tests/__init__.py
tests/test_analyzer.py
tests/test_stats.py
textinsights/__init__.py
textinsights/analyzer.py
textinsights/stats.py
textinsights/visualizer.py
textinsights-0.1.0.dist-info/licenses/LICENSE
textinsights-0.1.0.dist-info/METADATA
textinsights-0.1.0.dist-info/WHEEL
textinsights-0.1.0.dist-info/top_level.txt
textinsights-0.1.0.dist-info/RECORD
