Metadata-Version: 2.4
Name: textinsights
Version: 0.1.0
Summary: A package for text analysis and visualization
Home-page: https://github.com/ksg-dev/textinsights
Author: ksg-dev
Author-email: ksg.dev.data@gmail.com
Classifier: Programming Language :: Python :: 3
Classifier: License :: OSI Approved :: MIT License
Classifier: Operating System :: OS Independent
Classifier: Topic :: Text Processing :: Linguistic
Requires-Python: >=3.6
License-File: LICENSE
Requires-Dist: matplotlib>=3.4.0
Dynamic: author
Dynamic: author-email
Dynamic: classifier
Dynamic: description
Dynamic: description-content-type
Dynamic: home-page
Dynamic: license-file
Dynamic: requires-dist
Dynamic: requires-python
Dynamic: summary
